[
    {
        "_id": "615059baa59b4bb6566600c8",
        "index": 0,
        "guid": "f2855415-33ee-40fa-816f-31a66f42ffbf",
        "isActive": false,
        "balance": "$1,617.22",
        "picture": "https://www.nasa.gov/sites/default/files/styles/673xvariable_height/public/acd14-0002-005.jpg?itok=7Ecp8a-2",
        "age": 22,
        "eyeColor": "brown",
        "name": "Edith Willis",
        "gender": "female",
        "company": "SPEEDBOLT",
        "email": "edithwillis@speedbolt.com",
        "phone": "+1 (858) 588-2839",
        "address": "596 Legion Street, Chamberino, North Carolina, 892",
        "about": "Ullamco eu enim aliqua eiusmod velit id ipsum et. Cupidatat minim officia excepteur amet enim magna Lorem sint. Enim eiusmod proident cupidatat eu officia ipsum Lorem proident consectetur amet non veniam dolor. In anim in tempor nostrud anim deserunt consectetur labore esse laborum. Non tempor voluptate ad duis labore non ullamco exercitation cupidatat amet exercitation ex. Ex aliquip ea est dolor nulla. Sunt aute consequat nulla nostrud ad velit.\r\n",
        "registered": "2020-01-06T10:38:21 -06:00",
        "latitude": 36.736318,
        "longitude": -136.136768,
        "tags": [
            "laboris",
            "ullamco",
            "qui",
            "aliqua",
            "ea",
            "reprehenderit",
            "cillum"
        ],
        "friends": [
            {
                "id": 0,
                "name": "Carter Dixon"
            },
            {
                "id": 1,
                "name": "Madeline Carlson"
            },
            {
                "id": 2,
                "name": "Dorthy Bean"
            }
        ],
        "greeting": "Hello, Edith Willis! You have 3 unread messages.",
        "favoriteFruit": "apple"
    },
    {
        "_id": "615059baf4358cf0cc12c980",
        "index": 1,
        "guid": "c4acba51-658c-44a1-836a-eb7c0736e3d4",
        "isActive": true,
        "balance": "$3,710.99",
        "picture": "https://www.montana.edu/assets/images/16n7x/image3.jpg",
        "age": 39,
        "eyeColor": "green",
        "name": "Rivas Oneal",
        "gender": "male",
        "company": "EMPIRICA",
        "email": "rivasoneal@empirica.com",
        "phone": "+1 (989) 464-3405",
        "address": "146 Veranda Place, Babb, California, 2411",
        "about": "Velit nisi anim quis officia do nostrud est. Ex ullamco in pariatur occaecat tempor voluptate aliqua culpa esse consequat. Tempor ut reprehenderit cupidatat voluptate exercitation qui consequat veniam reprehenderit eiusmod esse. Minim exercitation ullamco qui cupidatat enim consectetur eu dolore officia aute fugiat. Duis laborum et ipsum consectetur dolore reprehenderit.\r\n",
        "registered": "2015-01-30T05:46:38 -06:00",
        "latitude": -55.731824,
        "longitude": 179.143922,
        "tags": [
            "mollit",
            "velit",
            "officia",
            "dolore",
            "adipisicing",
            "consectetur",
            "non"
        ],
        "friends": [
            {
                "id": 0,
                "name": "Crawford Bush"
            },
            {
                "id": 1,
                "name": "Petersen Shannon"
            },
            {
                "id": 2,
                "name": "Jo Guthrie"
            }
        ],
        "greeting": "Hello, Rivas Oneal! You have 2 unread messages.",
        "favoriteFruit": "apple"
    },
    {
        "_id": "615059ba3303a14ff9efc22e",
        "index": 2,
        "guid": "6e27977f-56f0-4071-8210-585794d16023",
        "isActive": true,
        "balance": "$2,925.74",
        "picture": "https://encrypted-tbn0.gstatic.com/images?q=tbn:ANd9GcTm5mYDb0S8Hku-9-ZqkYC_IOvF2kg4cbMAig&usqp=CAU",
        "age": 20,
        "eyeColor": "brown",
        "name": "Vasquez Dale",
        "gender": "male",
        "company": "UNDERTAP",
        "email": "vasquezdale@undertap.com",
        "phone": "+1 (819) 483-2013",
        "address": "206 Onderdonk Avenue, Emerald, American Samoa, 2754",
        "about": "Adipisicing est ipsum commodo non non esse ea proident deserunt tempor. Duis excepteur dolore ullamco pariatur ea adipisicing officia. Enim duis labore nostrud eiusmod consequat ex aliquip velit consequat laboris anim qui ad. Adipisicing qui excepteur sit culpa ut. Deserunt proident labore tempor consectetur eiusmod ipsum exercitation eu ipsum.\r\n",
        "registered": "2019-07-22T04:49:07 -06:00",
        "latitude": 74.376644,
        "longitude": -139.645619,
        "tags": [
            "mollit",
            "nostrud",
            "labore",
            "labore",
            "voluptate",
            "Lorem",
            "ullamco"
        ],
        "friends": [
            {
                "id": 0,
                "name": "Heather Dotson"
            },
            {
                "id": 1,
                "name": "Mendez Morton"
            },
            {
                "id": 2,
                "name": "Sanders Owens"
            }
        ],
        "greeting": "Hello, Vasquez Dale! You have 2 unread messages.",
        "favoriteFruit": "apple"
    },
    {
        "_id": "615059ba2919204b45a2e4d9",
        "index": 3,
        "guid": "63322090-518f-40a8-9311-9f9e2cfcd4bb",
        "isActive": false,
        "balance": "$1,034.92",
        "picture": "https://www.presby.edu/about/wp-content/uploads/sites/2/2018/03/clay-photo-student-profile-lego-math-nasa-2107_6.jpg",
        "age": 33,
        "eyeColor": "blue",
        "name": "Daphne Henderson",
        "gender": "female",
        "company": "GEOFORM",
        "email": "daphnehenderson@geoform.com",
        "phone": "+1 (814) 559-2320",
        "address": "312 Losee Terrace, Bladensburg, Michigan, 7073",
        "about": "Nostrud voluptate magna amet duis aute culpa deserunt voluptate. Deserunt quis esse eu exercitation deserunt minim laboris dolore. Nulla Lorem et ea esse adipisicing laboris consequat dolore enim cupidatat. Irure dolore esse quis commodo dolore minim. Voluptate et nisi irure nisi. Id in mollit enim adipisicing ut ea sit laboris duis sit pariatur quis. Incididunt commodo qui elit sint sint aliqua occaecat reprehenderit ea cillum ipsum id excepteur.\r\n",
        "registered": "2017-06-02T10:29:42 -06:00",
        "latitude": 31.6957,
        "longitude": -157.938132,
        "tags": [
            "exercitation",
            "do",
            "eu",
            "eu",
            "irure",
            "nulla",
            "reprehenderit"
        ],
        "friends": [
            {
                "id": 0,
                "name": "Vicky Wagner"
            },
            {
                "id": 1,
                "name": "Arnold Ewing"
            },
            {
                "id": 2,
                "name": "Margie Massey"
            }
        ],
        "greeting": "Hello, Daphne Henderson! You have 1 unread messages.",
        "favoriteFruit": "apple"
    },
    {
        "_id": "615059bae20b346a11b65eec",
        "index": 4,
        "guid": "b2309803-38f2-4d5e-a6e7-1869d10e4114",
        "isActive": true,
        "balance": "$1,474.17",
        "picture": "https://encrypted-tbn0.gstatic.com/images?q=tbn:ANd9GcS78nDr-637HsHfYgI2lrRUhNmUWzwHdutMnA&usqp=CAU",
        "age": 29,
        "eyeColor": "brown",
        "name": "Mollie Ortega",
        "gender": "female",
        "company": "ZYTRAX",
        "email": "mollieortega@zytrax.com",
        "phone": "+1 (971) 573-3889",
        "address": "711 Richards Street, Fresno, Pennsylvania, 7870",
        "about": "Qui ipsum fugiat minim sint non culpa consequat velit consequat nisi minim. Duis nulla exercitation aliquip magna esse culpa eu ex enim. Ipsum occaecat sint sunt exercitation et eu quis ut enim occaecat ut ipsum esse.\r\n",
        "registered": "2021-07-07T05:06:26 -06:00",
        "latitude": -75.431879,
        "longitude": 157.856632,
        "tags": [
            "minim",
            "nisi",
            "sit",
            "elit",
            "amet",
            "adipisicing",
            "non"
        ],
        "friends": [
            {
                "id": 0,
                "name": "Cohen Fields"
            },
            {
                "id": 1,
                "name": "Haley Hicks"
            },
            {
                "id": 2,
                "name": "Mathis Shaw"
            }
        ],
        "greeting": "Hello, Mollie Ortega! You have 3 unread messages.",
        "favoriteFruit": "banana"
    },
    {
        "_id": "615059ba0041e3556014786c",
        "index": 5,
        "guid": "718db084-b3c1-40e6-a1e1-d566db977743",
        "isActive": true,
        "balance": "$2,496.40",
        "picture": "https://encrypted-tbn0.gstatic.com/images?q=tbn:ANd9GcSTgNiXsU_dEJeB0OUGKCW_Jo1Ov-CWVnnfHg&usqp=CAU",
        "age": 26,
        "eyeColor": "green",
        "name": "Suzanne Harris",
        "gender": "female",
        "company": "DIGIPRINT",
        "email": "suzanneharris@digiprint.com",
        "phone": "+1 (996) 486-3982",
        "address": "998 Clay Street, Matheny, Colorado, 1490",
        "about": "Ut non ea ex ad quis fugiat adipisicing nostrud consectetur aute ex tempor. Quis exercitation labore occaecat ex consequat. Nulla esse duis mollit excepteur enim id occaecat mollit commodo adipisicing do tempor duis.\r\n",
        "registered": "2015-04-27T11:01:47 -06:00",
        "latitude": -21.702076,
        "longitude": 152.15518,
        "tags": [
            "est",
            "labore",
            "pariatur",
            "id",
            "elit",
            "enim",
            "voluptate"
        ],
        "friends": [
            {
                "id": 0,
                "name": "Dona Donaldson"
            },
            {
                "id": 1,
                "name": "Stark Baxter"
            },
            {
                "id": 2,
                "name": "Mitzi Finley"
            }
        ],
        "greeting": "Hello, Suzanne Harris! You have 2 unread messages.",
        "favoriteFruit": "banana"
    },
    {
        "_id": "615059ba92587a2b59afb13a",
        "index": 6,
        "guid": "3390794e-4510-48d1-b721-ff7f280689b7",
        "isActive": false,
        "balance": "$1,501.51",
        "picture": "https://www.ucf.edu/news/files/2015/02/DSC_0001-e1423845216919-768x512.jpg",
        "age": 30,
        "eyeColor": "brown",
        "name": "Renee Clay",
        "gender": "female",
        "company": "KRAG",
        "email": "reneeclay@krag.com",
        "phone": "+1 (951) 597-3090",
        "address": "197 Howard Alley, Whipholt, Alaska, 3729",
        "about": "Sint sunt sunt mollit occaecat ea eu aliquip voluptate sint aliquip exercitation amet. Ex in nulla quis reprehenderit proident dolor. Ad ex Lorem nisi ipsum excepteur ex sit cillum pariatur dolor anim. Ullamco reprehenderit minim sunt amet ipsum voluptate est eiusmod ad occaecat pariatur. Tempor aliqua laborum eu consequat aliquip dolore qui adipisicing deserunt.\r\n",
        "registered": "2019-01-14T12:39:27 -06:00",
        "latitude": 20.15929,
        "longitude": -42.272544,
        "tags": [
            "ut",
            "ipsum",
            "elit",
            "dolor",
            "amet",
            "sit",
            "aute"
        ],
        "friends": [
            {
                "id": 0,
                "name": "Freeman Baker"
            },
            {
                "id": 1,
                "name": "Camille Richardson"
            },
            {
                "id": 2,
                "name": "Tate Carney"
            }
        ],
        "greeting": "Hello, Renee Clay! You have 7 unread messages.",
        "favoriteFruit": "banana"
    },
    {
        "_id": "615059ba6718781ee208015f",
        "index": 7,
        "guid": "a3381545-6a4c-433f-9c4d-da725f6fa5bc",
        "isActive": false,
        "balance": "$2,611.78",
        "picture": "https://www.ucf.edu/news/files/2020/05/UCF-Adrienne-Dove-1-234x300.jpg",
        "age": 23,
        "eyeColor": "green",
        "name": "Amanda Morrison",
        "gender": "female",
        "company": "INSURESYS",
        "email": "amandamorrison@insuresys.com",
        "phone": "+1 (883) 545-2529",
        "address": "494 Fulton Street, Loomis, Connecticut, 5466",
        "about": "Quis eiusmod consequat et reprehenderit et id elit consequat eu. Reprehenderit consequat enim et reprehenderit commodo sint aute exercitation non et quis commodo officia voluptate. Ad cillum Lorem aliqua exercitation amet anim elit esse incididunt magna exercitation labore. Id cupidatat duis sunt elit dolore ullamco exercitation id dolor pariatur excepteur ipsum quis. Id nostrud laborum ipsum occaecat commodo.\r\n",
        "registered": "2014-02-03T11:59:51 -06:00",
        "latitude": -65.91812,
        "longitude": 30.941822,
        "tags": [
            "aute",
            "cupidatat",
            "commodo",
            "laborum",
            "eu",
            "dolor",
            "aliquip"
        ],
        "friends": [
            {
                "id": 0,
                "name": "Franklin Mayo"
            },
            {
                "id": 1,
                "name": "Gould Gilliam"
            },
            {
                "id": 2,
                "name": "Malone Curtis"
            }
        ],
        "greeting": "Hello, Amanda Morrison! You have 4 unread messages.",
        "favoriteFruit": "strawberry"
    },
    {
        "_id": "615059baf5296888256b0f89",
        "index": 8,
        "guid": "a45eefad-c3ec-4def-aa15-3910fa9de99d",
        "isActive": true,
        "balance": "$3,595.24",
        "picture": "https://encrypted-tbn0.gstatic.com/images?q=tbn:ANd9GcThkLj_CXRycDWxIqStOQkw8EgTfnvolp1dDQ&usqp=CAU",
        "age": 31,
        "eyeColor": "blue",
        "name": "Cara Fitzpatrick",
        "gender": "female",
        "company": "SYBIXTEX",
        "email": "carafitzpatrick@sybixtex.com",
        "phone": "+1 (994) 495-3424",
        "address": "526 Eagle Street, Harborton, Texas, 6648",
        "about": "Aliquip velit consequat aute reprehenderit officia eiusmod commodo ex eu eiusmod pariatur ex sunt exercitation. Amet consectetur id minim mollit ea ut minim dolor aute labore sint. Eiusmod magna ipsum eu voluptate officia id incididunt deserunt. Deserunt minim veniam pariatur velit ea quis sint. Anim enim veniam proident consequat elit dolore elit mollit. Proident irure est consectetur deserunt sint labore cillum voluptate excepteur duis esse eu aliquip et. Veniam dolor id culpa laborum exercitation ullamco anim laborum ea amet nulla pariatur adipisicing.\r\n",
        "registered": "2020-07-02T10:27:43 -06:00",
        "latitude": 27.107938,
        "longitude": -150.863684,
        "tags": [
            "ullamco",
            "incididunt",
            "ex",
            "tempor",
            "sint",
            "eiusmod",
            "sunt"
        ],
        "friends": [
            {
                "id": 0,
                "name": "Stacie Pickett"
            },
            {
                "id": 1,
                "name": "Magdalena Bernard"
            },
            {
                "id": 2,
                "name": "Kelli Kennedy"
            }
        ],
        "greeting": "Hello, Cara Fitzpatrick! You have 7 unread messages.",
        "favoriteFruit": "banana"
    },
    {
        "_id": "615059ba2feb5e99031e0916",
        "index": 9,
        "guid": "fc97d102-e67f-48dc-87db-7452dd26f9c6",
        "isActive": true,
        "balance": "$2,881.33",
        "picture": "https://encrypted-tbn0.gstatic.com/images?q=tbn:ANd9GcTujN1sP6Fu5_xryr9GwGpxB8GDkEkgsZe-bg&usqp=CAU",
        "age": 20,
        "eyeColor": "blue",
        "name": "Cooper Kline",
        "gender": "male",
        "company": "QUILTIGEN",
        "email": "cooperkline@quiltigen.com",
        "phone": "+1 (825) 558-3091",
        "address": "794 George Street, Brutus, Wisconsin, 6947",
        "about": "Id reprehenderit enim officia ipsum. Aliquip labore aute nulla amet labore commodo minim sint nisi nisi cupidatat. Qui anim laborum ullamco fugiat elit nulla irure eu eiusmod occaecat elit.\r\n",
        "registered": "2014-05-12T06:11:36 -06:00",
        "latitude": -27.621668,
        "longitude": -54.634022,
        "tags": [
            "in",
            "fugiat",
            "duis",
            "ea",
            "laborum",
            "labore",
            "duis"
        ],
        "friends": [
            {
                "id": 0,
                "name": "Roslyn Andrews"
            },
            {
                "id": 1,
                "name": "Tammy Dunn"
            },
            {
                "id": 2,
                "name": "Sims Montoya"
            }
        ],
        "greeting": "Hello, Cooper Kline! You have 9 unread messages.",
        "favoriteFruit": "apple"
    },
    {
        "_id": "615059ba64c966722dc78848",
        "index": 10,
        "guid": "9899274b-1299-483d-98d8-ca11f7fd8aea",
        "isActive": false,
        "balance": "$1,768.93",
        "picture": "https://encrypted-tbn0.gstatic.com/images?q=tbn:ANd9GcQfqBf8CSMG5teNxjkdPDUZJg-o7jIm3P3qZQ&usqp=CAU",
        "age": 33,
        "eyeColor": "blue",
        "name": "Tamara Rodgers",
        "gender": "female",
        "company": "BESTO",
        "email": "tamararodgers@besto.com",
        "phone": "+1 (857) 581-2144",
        "address": "387 Falmouth Street, Urbana, New York, 8686",
        "about": "Nulla id excepteur ad commodo minim proident eiusmod non. Aliquip incididunt eu eiusmod laborum aliqua. Reprehenderit id velit esse labore veniam mollit sint eiusmod excepteur pariatur est. Dolor dolore est exercitation quis velit pariatur reprehenderit tempor ea amet.\r\n",
        "registered": "2018-06-04T09:24:09 -06:00",
        "latitude": -12.882545,
        "longitude": 109.340538,
        "tags": [
            "commodo",
            "cillum",
            "exercitation",
            "deserunt",
            "id",
            "non",
            "duis"
        ],
        "friends": [
            {
                "id": 0,
                "name": "Brenda Cole"
            },
            {
                "id": 1,
                "name": "Mable Hendrix"
            },
            {
                "id": 2,
                "name": "Nguyen Decker"
            }
        ],
        "greeting": "Hello, Tamara Rodgers! You have 7 unread messages.",
        "favoriteFruit": "banana"
    },
    {
        "_id": "615059ba09ad7e4369c2788b",
        "index": 11,
        "guid": "5c2995a2-0055-461d-ac3c-97e1ed18c3d1",
        "isActive": false,
        "balance": "$1,132.49",
        "picture": "https://www.montana.edu/assets/images/16n7x/image3.jpg",
        "age": 39,
        "eyeColor": "brown",
        "name": "Clayton Vasquez",
        "gender": "male",
        "company": "BLURRYBUS",
        "email": "claytonvasquez@blurrybus.com",
        "phone": "+1 (863) 509-2332",
        "address": "937 Beverly Road, Bainbridge, Illinois, 7864",
        "about": "Labore aute adipisicing in anim. Cupidatat do duis sit magna. Minim ipsum ut quis consequat consectetur commodo quis ullamco incididunt. Adipisicing magna minim aute occaecat incididunt ut. Laboris sit laborum do ullamco dolor fugiat quis sint veniam nostrud adipisicing Lorem. In reprehenderit Lorem eu Lorem sint enim adipisicing mollit eu quis.\r\n",
        "registered": "2014-08-01T11:37:41 -06:00",
        "latitude": 46.969386,
        "longitude": 172.114785,
        "tags": [
            "occaecat",
            "velit",
            "occaecat",
            "ipsum",
            "esse",
            "cupidatat",
            "mollit"
        ],
        "friends": [
            {
                "id": 0,
                "name": "Alexis Anthony"
            },
            {
                "id": 1,
                "name": "Wade Atkins"
            },
            {
                "id": 2,
                "name": "Selma Huff"
            }
        ],
        "greeting": "Hello, Clayton Vasquez! You have 2 unread messages.",
        "favoriteFruit": "banana"
    },
    {
        "_id": "615059bac3487d8c1be24fc9",
        "index": 12,
        "guid": "a340a6ac-6eb9-4851-b802-78de47948d97",
        "isActive": true,
        "balance": "$1,948.25",
        "picture": "http://www.nasa.gov/sites/default/files/hrp-harrison-microscope-3d6340606-cropped_0.jpg",
        "age": 34,
        "eyeColor": "blue",
        "name": "Helen Mack",
        "gender": "female",
        "company": "NORALI",
        "email": "helenmack@norali.com",
        "phone": "+1 (827) 536-2921",
        "address": "774 Bridgewater Street, Succasunna, New Hampshire, 6029",
        "about": "Sint qui dolor occaecat cillum deserunt voluptate deserunt sint veniam eiusmod duis duis adipisicing. Magna exercitation dolore elit excepteur aute. Aliquip in anim nulla mollit amet enim sint ut non laboris ullamco ad elit.\r\n",
        "registered": "2014-12-14T08:08:23 -06:00",
        "latitude": 61.449615,
        "longitude": 21.696078,
        "tags": [
            "ullamco",
            "commodo",
            "irure",
            "qui",
            "nulla",
            "ad",
            "sunt"
        ],
        "friends": [
            {
                "id": 0,
                "name": "Mayra Nelson"
            },
            {
                "id": 1,
                "name": "May Barr"
            },
            {
                "id": 2,
                "name": "Nettie Talley"
            }
        ],
        "greeting": "Hello, Helen Mack! You have 1 unread messages.",
        "favoriteFruit": "strawberry"
    },
    {
        "_id": "615059bacac7519117f50a3d",
        "index": 13,
        "guid": "66884b2a-d971-4def-b00d-63e1ecb1156a",
        "isActive": true,
        "balance": "$3,524.14",
        "picture": "https://www.nasa.gov/centers/langley/images/content/108395main_fishman300.jpg",
        "age": 35,
        "eyeColor": "brown",
        "name": "Ramona Humphrey",
        "gender": "female",
        "company": "ZAGGLES",
        "email": "ramonahumphrey@zaggles.com",
        "phone": "+1 (807) 495-2951",
        "address": "375 Lewis Avenue, Highland, Massachusetts, 9943",
        "about": "Mollit sint sit ipsum nulla eiusmod ut esse duis excepteur proident duis laboris cupidatat. Ad deserunt culpa tempor nisi. Consectetur id adipisicing irure dolor incididunt. Mollit magna est qui ullamco ullamco esse deserunt ex commodo proident reprehenderit qui eiusmod ipsum. Laborum ut consectetur id non proident cupidatat eu in ipsum non incididunt. Esse duis proident minim consectetur qui.\r\n",
        "registered": "2016-04-26T01:43:59 -06:00",
        "latitude": -6.391106,
        "longitude": 103.553393,
        "tags": [
            "sunt",
            "esse",
            "veniam",
            "enim",
            "est",
            "ut",
            "ullamco"
        ],
        "friends": [
            {
                "id": 0,
                "name": "Brady Mcneil"
            },
            {
                "id": 1,
                "name": "Tracy Clarke"
            },
            {
                "id": 2,
                "name": "Craft Ramirez"
            }
        ],
        "greeting": "Hello, Ramona Humphrey! You have 8 unread messages.",
        "favoriteFruit": "apple"
    },
    {
        "_id": "615059ba9fd68cfe80483b8e",
        "index": 14,
        "guid": "2bf4bb37-1018-49b4-a31d-c7776935658e",
        "isActive": false,
        "balance": "$3,709.68",
        "picture": "https://encrypted-tbn0.gstatic.com/images?q=tbn:ANd9GcTkgIucLQqxYXb_GPhBNu5a9qFIJJE-qvKjWA&usqp=CAU",
        "age": 38,
        "eyeColor": "green",
        "name": "Workman Duran",
        "gender": "male",
        "company": "TALKALOT",
        "email": "workmanduran@talkalot.com",
        "phone": "+1 (921) 513-3471",
        "address": "642 Roder Avenue, Brandermill, Virginia, 4034",
        "about": "Sunt velit pariatur ad cillum enim commodo ipsum officia dolor veniam nulla mollit aliquip minim. Velit esse nisi deserunt Lorem id incididunt Lorem quis ullamco. Fugiat excepteur ipsum esse voluptate exercitation nulla quis quis elit nulla proident velit elit nostrud. In amet cillum do dolore velit cillum sint nulla exercitation cillum et duis pariatur qui. Officia est non amet minim nisi. Ut sint tempor pariatur enim quis esse laborum commodo sint laboris reprehenderit. Ex sunt pariatur pariatur proident amet ex.\r\n",
        "registered": "2019-05-25T09:11:04 -06:00",
        "latitude": -18.147146,
        "longitude": 102.989278,
        "tags": [
            "culpa",
            "adipisicing",
            "ex",
            "aliquip",
            "consectetur",
            "aute",
            "culpa"
        ],
        "friends": [
            {
                "id": 0,
                "name": "Dee Valenzuela"
            },
            {
                "id": 1,
                "name": "Owens Melton"
            },
            {
                "id": 2,
                "name": "Manuela Riddle"
            }
        ],
        "greeting": "Hello, Workman Duran! You have 4 unread messages.",
        "favoriteFruit": "strawberry"
    }
]